django_clickhouse/__init__.py
django_clickhouse/clickhouse_models.py
django_clickhouse/compatibility.py
django_clickhouse/configuration.py
django_clickhouse/database.py
django_clickhouse/engines.py
django_clickhouse/exceptions.py
django_clickhouse/migrations.py
django_clickhouse/models.py
django_clickhouse/query.py
django_clickhouse/redis.py
django_clickhouse/routers.py
django_clickhouse/serializers.py
django_clickhouse/storages.py
django_clickhouse/tasks.py
django_clickhouse/utils.py
django_clickhouse/management/commands/__init__.py
django_clickhouse/management/commands/clickhouse_migrate.py
django_clickhouse-1.2.1.dist-info/LICENSE
django_clickhouse-1.2.1.dist-info/METADATA
django_clickhouse-1.2.1.dist-info/WHEEL
django_clickhouse-1.2.1.dist-info/top_level.txt
django_clickhouse-1.2.1.dist-info/RECORD
