Metadata-Version: 2.1
Name: django-clickhouse
Version: 1.2.1
Summary: Django extension to integrate with ClickHouse database
Home-page: https://github.com/carrotquest/django-clickhouse
Author: Carrot quest
Author-email: m1ha@carrotquest.io
License: BSD 3-clause "New" or "Revised" License
License-File: LICENSE
